gui_image_studio/__init__.py
gui_image_studio/__main__.py
gui_image_studio/cli.py
gui_image_studio/embedded_images.py
gui_image_studio/generator.py
gui_image_studio/image_loader.py
gui_image_studio/image_studio.py
gui_image_studio/py.typed
gui_image_studio/sample_creator.py
gui_image_studio-1.0.1.dist-info/licenses/LICENSE
gui_image_studio-1.0.1.dist-info/METADATA
gui_image_studio-1.0.1.dist-info/WHEEL
gui_image_studio-1.0.1.dist-info/entry_points.txt
gui_image_studio-1.0.1.dist-info/top_level.txt
gui_image_studio-1.0.1.dist-info/RECORD
