Metadata-Version: 2.4
Name: gui-image-studio
Version: 1.0.1
Summary: GUI Image Studio - Complete toolkit for creating, embedding, and managing images in Python GUI applications
Home-page: https://github.com/stntg/gui-image-studio
Author: Stan Griffiths
Author-email: Stan Griffiths <stantgriffiths@gmail.com>
Maintainer-email: Stan Griffiths <stantgriffiths@gmail.com>
License: MIT
Project-URL: Homepage, https://github.com/stntg/gui-image-studio
Project-URL: Documentation, https://github.com/stntg/gui-image-studio#readme
Project-URL: Repository, https://github.com/stntg/gui-image-studio
Project-URL: Bug Reports, https://github.com/stntg/gui-image-studio/issues
Keywords: image,gui,tkinter,customtkinter,embed,resources,PIL,Pillow
Classifier: Development Status :: 4 - Beta
Classifier: Intended Audience :: Developers
Classifier: Topic :: Software Development :: Libraries :: Python Modules
Classifier: Topic :: Multimedia :: Graphics
Classifier: Topic :: Software Development :: User Interfaces
Classifier: License :: OSI Approved :: MIT License
Classifier: Programming Language :: Python :: 3
Classifier: Programming Language :: Python :: 3.8
Classifier: Programming Language :: Python :: 3.9
Classifier: Programming Language :: Python :: 3.10
Classifier: Programming Language :: Python :: 3.11
Classifier: Programming Language :: Python :: 3.12
Classifier: Operating System :: OS Independent
Requires-Python: >=3.8
License-File: LICENSE
Requires-Dist: Pillow>=8.0.0
Provides-Extra: customtkinter
Requires-Dist: customtkinter>=5.0.0; extra == "customtkinter"
Provides-Extra: dev
Requires-Dist: pytest>=7.0; extra == "dev"
Requires-Dist: pytest-cov>=4.0; extra == "dev"
Requires-Dist: pytest-xvfb>=2.0; sys_platform == "linux" and extra == "dev"
Requires-Dist: pytest-timeout>=2.0; extra == "dev"
Requires-Dist: black>=22.0; extra == "dev"
Requires-Dist: flake8>=5.0; extra == "dev"
Requires-Dist: mypy>=1.0; extra == "dev"
Requires-Dist: isort>=5.0; extra == "dev"
Requires-Dist: pre-commit>=2.20; extra == "dev"
Requires-Dist: bandit>=1.7; extra == "dev"
Requires-Dist: safety>=2.0; extra == "dev"
Requires-Dist: tox>=4.0; extra == "dev"
Provides-Extra: docs
Requires-Dist: sphinx>=5.0; extra == "docs"
Requires-Dist: sphinx-rtd-theme>=1.0; extra == "docs"
Requires-Dist: myst-parser>=0.18; extra == "docs"
Requires-Dist: sphinx-autodoc-typehints>=1.19; extra == "docs"
Requires-Dist: sphinx-copybutton>=0.5; extra == "docs"
Provides-Extra: test
Requires-Dist: pytest>=7.0; extra == "test"
Requires-Dist: pytest-cov>=4.0; extra == "test"
Requires-Dist: pytest-xvfb>=2.0; sys_platform == "linux" and extra == "test"
Requires-Dist: pytest-timeout>=2.0; extra == "test"
Provides-Extra: examples
Requires-Dist: customtkinter>=5.0.0; extra == "examples"
Dynamic: author
Dynamic: home-page
Dynamic: license-file
Dynamic: requires-python
